CHANGES.txt
LICENSE.txt
MANIFEST.in
README.txt
setup.py
src/m01/__init__.py
src/m01.searcher.egg-info/PKG-INFO
src/m01.searcher.egg-info/SOURCES.txt
src/m01.searcher.egg-info/dependency_links.txt
src/m01.searcher.egg-info/namespace_packages.txt
src/m01.searcher.egg-info/not-zip-safe
src/m01.searcher.egg-info/requires.txt
src/m01.searcher.egg-info/top_level.txt
src/m01/searcher/README.txt
src/m01/searcher/__init__.py
src/m01/searcher/criterion.py
src/m01/searcher/filter.py
src/m01/searcher/interfaces.py
src/m01/searcher/session.py
src/m01/searcher/testing.py
src/m01/searcher/tests.py