Metadata-Version: 1.0
Name: m01.searcher
Version: 0.5.1
Summary: MongoDB searcher search filter implementation for Zope3
Home-page: http://pypi.python.org/pypi/m01.searcher
Author: Roger Ineichen, Projekt01 GmbH
Author-email: dev@projekt01.ch
License: ZPL 2.1
Keywords: Zope3 z3c p01 m01 mongo search filter
Platform: UNKNOWN
Classifier: Development Status :: 4 - Beta
Classifier: Environment :: Web Environment
Classifier: Intended Audience :: Developers
Classifier: License :: OSI Approved :: Zope Public License
Classifier: Programming Language :: Python
Classifier: Natural Language :: English
Classifier: Operating System :: OS Independent
Classifier: Topic :: Internet :: WWW/HTTP
Classifier: Framework :: Zope3
